banal/__init__.py
banal/bools.py
banal/cache.py
banal/dicts.py
banal/filesystem.py
banal/lists.py
banal/py.typed
banal-1.0.6.dist-info/LICENSE
banal-1.0.6.dist-info/METADATA
banal-1.0.6.dist-info/WHEEL
banal-1.0.6.dist-info/namespace_packages.txt
banal-1.0.6.dist-info/top_level.txt
banal-1.0.6.dist-info/RECORD
